{ "_id" : "hv1VEDDgROJt9lyGNjgGbWDq-VoKYkav", "expires" : { "$date" : "2019-12-26T02:15:26.951+0000" }, "session" : "{\"cookie\":{\"originalMaxAge\":1209600000,\"expires\":\"2019-12-26T02:07:10.998Z\",\"httpOnly\":true,\"path\":\"/\"},\"flash\":{},\"passport\":{\"user\":1},\"meta\":{\"ip\":\"127.0.0.1\",\"uuid\":\"6b133960-54f8-4dec-bb25-37f5e27a392c\",\"datetime\":1576055726398,\"platform\":\"Linux\",\"browser\":\"Chromium\",\"version\":\"78.0.3904.108\"},\"returnTo\":\"/admin\",\"forceLogin\":1,\"uids_viewed\":{}}" }
{ "_id" : "JKg338JPk09qcJCjRSdwzb-ptP9aDU3Y", "expires" : { "$date" : "2020-01-08T09:12:43.284+0000" }, "session" : "{\"cookie\":{\"originalMaxAge\":1209600000,\"expires\":\"2020-01-08T07:41:12.209Z\",\"httpOnly\":true,\"path\":\"/\"},\"flash\":{},\"referrer\":\"/\",\"passport\":{\"user\":2},\"meta\":{\"ip\":\"127.0.0.1\",\"uuid\":\"de9a5043-42ec-4a1a-a566-894803c45adb\",\"datetime\":1577258894070,\"platform\":\"Linux\",\"browser\":\"Chrome\",\"version\":\"78.0.3904.70\"},\"returnTo\":\"/\",\"tids_viewed\":{\"2\":1577258898896,\"3\":1577259672208},\"uids_viewed\":{\"1\":1577259414495}}" }
{ "_id" : "EX2UJYESZR9ZIpvQUsPjxBAr69vvTs6t", "expires" : { "$date" : "2020-01-08T09:46:50.773+0000" }, "session" : "{\"cookie\":{\"originalMaxAge\":1209600000,\"expires\":\"2020-01-08T09:43:12.666Z\",\"httpOnly\":true,\"path\":\"/\"},\"flash\":{},\"passport\":{\"user\":2},\"meta\":{\"ip\":\"127.0.0.1\",\"uuid\":\"ef93349c-7974-4781-8207-baf4e5b6e2b3\",\"datetime\":1577266992557,\"platform\":\"Linux\",\"browser\":\"Chrome\",\"version\":\"78.0.3904.70\"},\"uids_viewed\":{}}" }
{ "_id" : "TBuDhAWEIJnj4nnqBC_Vug4Ha1fo0ylL", "expires" : { "$date" : "2020-01-08T10:10:24.038+0000" }, "session" : "{\"cookie\":{\"originalMaxAge\":1209600000,\"expires\":\"2020-01-08T09:49:57.092Z\",\"httpOnly\":true,\"path\":\"/\"},\"flash\":{},\"passport\":{\"user\":2},\"meta\":{\"ip\":\"127.0.0.1\",\"uuid\":\"a283d114-82d0-44b1-ae66-17908b30d88d\",\"datetime\":1577267397070,\"platform\":\"Linux\",\"browser\":\"Chrome\",\"version\":\"78.0.3904.70\"}}" }
{ "_id" : "pS0sAnnfElCYbRgGTdUs0KM0xqxetSJE", "expires" : { "$date" : "2020-01-08T10:14:03.927+0000" }, "session" : "{\"cookie\":{\"originalMaxAge\":1209600000,\"expires\":\"2020-01-08T10:14:03.927Z\",\"httpOnly\":true,\"path\":\"/\"},\"returnTo\":\"/\",\"flash\":{},\"ssoState\":\"MBVzpatx-8dm6l6mBGjWggY7NayeVgIt9Dxw\"}" }
